di_container_ibragimoff/__init__.py
di_container_ibragimoff/container.py
di_container_ibragimoff/container_exceptions.py
di_container_ibragimoff-0.0.3.dist-info/METADATA
di_container_ibragimoff-0.0.3.dist-info/WHEEL
di_container_ibragimoff-0.0.3.dist-info/licenses/LICENSE
di_container_ibragimoff-0.0.3.dist-info/RECORD
